backtesting/__init__.py
backtesting/_plotting.py
backtesting/_stats.py
backtesting/_util.py
backtesting/_version.py
backtesting/autoscale_cb.js
backtesting/backtesting.py
backtesting/lib.py
backtesting/test/EURUSD.csv
backtesting/test/GOOG.csv
backtesting/test/__init__.py
backtesting/test/__main__.py
backtesting/test/_test.py
lucit_backtesting-1.0.0.dist-info/LICENSE.md
lucit_backtesting-1.0.0.dist-info/METADATA
lucit_backtesting-1.0.0.dist-info/WHEEL
lucit_backtesting-1.0.0.dist-info/top_level.txt
lucit_backtesting-1.0.0.dist-info/RECORD
