Metadata-Version: 2.1
Name: lucit-backtesting
Version: 1.0.0
Summary: Backtest trading strategies in Python
Home-page: https://github.com/LUCIT-Systems-and-Development/lucit-backtesting
Author: LUCIT Systems and Development
License: AGPL-3.0
Project-URL: Documentation, https://lucit-backtesting.docs.lucit.tech
Project-URL: Source, https://github.com/LUCIT-Systems-and-Development/lucit-backtesting
Project-URL: Wiki, https://github.com/LUCIT-Systems-and-Development/lucit-backtesting/wiki
Project-URL: Author, https://www.lucit.tech
Project-URL: Changes, https://lucit-backtesting.docs.lucit.tech/changelog.html
Project-URL: License, https://lucit-backtesting.docs.lucit.tech/license.html
Project-URL: Issue Tracker, https://github.com/LUCIT-Systems-and-Development/lucit-backtesting/issues
Project-URL: Telegram, https://t.me/unicorndevs
Project-URL: Get Support, https://www.lucit.tech/get-support.html
Keywords: algo,algorithmic,ashi,backtest,backtesting,bitcoin,bokeh,bonds,candle,candlestick,cboe,chart,cme,commodities,crash,crypto,currency,doji,drawdown,equity,etf,ethereum,exchange,finance,financial,forecast,forex,fund,futures,fx,fxpro,gold,heiken,historical,indicator,invest,investing,investment,macd,market,mechanical,money,oanda,ohlc,ohlcv,order,price,profit,quant,quantitative,rsi,silver,simulation,stocks,strategy,ticker,trader,trading,tradingview,usd
Classifier: Intended Audience :: Financial and Insurance Industry
Classifier: Intended Audience :: Science/Research
Classifier: Framework :: Jupyter
Classifier: License :: OSI Approved :: GNU Affero General Public License v3 or later (AGPLv3+)
Classifier: Operating System :: OS Independent
Classifier: Programming Language :: Python :: 3 :: Only
Classifier: Topic :: Office/Business :: Financial :: Investment
Classifier: Topic :: Scientific/Engineering :: Visualization
Requires-Python: >=3.6
License-File: LICENSE.md
Requires-Dist: numpy (>=1.17.0)
Requires-Dist: pandas (!=0.25.0,>=0.25.0)
Requires-Dist: bokeh (==2.4.3)
Provides-Extra: dev
Requires-Dist: ruff (==0.0.160) ; extra == 'dev'
Requires-Dist: coverage ; extra == 'dev'
Requires-Dist: mypy ; extra == 'dev'
Provides-Extra: doc
Requires-Dist: pdoc3 ; extra == 'doc'
Requires-Dist: jupytext (>=1.3) ; extra == 'doc'
Requires-Dist: nbconvert ; extra == 'doc'
Requires-Dist: ipykernel ; extra == 'doc'
Requires-Dist: jupyter-client ; extra == 'doc'
Provides-Extra: test
Requires-Dist: seaborn ; extra == 'test'
Requires-Dist: matplotlib ; extra == 'test'
Requires-Dist: scikit-learn (<=1.1.3) ; extra == 'test'
Requires-Dist: scikit-optimize ; extra == 'test'
